x_client_transaction/__init__.py
x_client_transaction/constants.py
x_client_transaction/cubic_curve.py
x_client_transaction/interpolate.py
x_client_transaction/rotation.py
x_client_transaction/transaction.py
x_client_transaction/utils.py
x_transaction_id_generator-1.0.0.dist-info/licenses/LICENSE
x_transaction_id_generator-1.0.0.dist-info/METADATA
x_transaction_id_generator-1.0.0.dist-info/WHEEL
x_transaction_id_generator-1.0.0.dist-info/top_level.txt
x_transaction_id_generator-1.0.0.dist-info/RECORD
